{"0": " ", "1": " ", "2": " ", "3": " ", "4": " ", "5": " ", "6": " ", "7": " ", "8": " ", "9": " ", "10": " ", "11": " ", "12": " ", "13": " ", "14": " ", "15": " ", "16": " ", "17": " ", "18": " ", "19": " ", "20": " ", "21": " ", "22": " ", "23": " ", "24": " ", "25": " ", "26": " ", "27": " ", "28": " ", "29": " ", "30": " ", "31": " ", "32": " ", "33": " ", "34": " ", "35": " ", "36": " ", "37": " ", "38": " ", "39": " ", "40": " ", "41": "`", "42": "`", "43": "`", "44": "`", "45": "`", "46": "`", "47": "`", "48": "`", "49": "`", "50": "`", "51": "`", "52": "`", "53": "`", "54": "`", "55": "`", "56": "`", "57": "`", "58": "`", "59": "`", "60": "`", "61": "`", "62": "`", "63": "`", "64": "`", "65": "`", "66": "`", "67": "`", "68": "`", "69": "`", "70": "`", "71": "`", "72": "`", "73": "`", "74": "`", "75": "`", "76": "`", "77": "`", "78": "`", "79": "`", "80": "`", "81": "`", "82": "`", "83": "`", "84": "`", "85": "`", "86": "`", "87": "`", "88": "`", "89": "`", "90": "`", "91": "'", "92": "'", "93": "'", "94": "'", "95": "'", "96": "'", "97": "'", "98": "'", "99": "'", "100": "'", "101": "'", "102": ".", "103": ".", "104": ".", "105": ".", "106": "-", "107": "-", "108": "-", "109": "-", "110": ",", "111": ",", "112": ",", "113": "_", "114": "_", "115": ":", "116": ":", "117": ":", "118": ":", "119": "!", "120": "!", "121": "^", "122": "\"", "123": "\"", "124": "\"", "125": ";", "126": ";", "127": ";", "128": "r", "129": "\\", "130": "+", "131": ")", "132": ">", "133": "|", "134": "=", "135": "?", "136": "c", "137": "i", "138": "i", "139": "v", "140": "z", "141": "L", "142": "s", "143": "}", "144": "Y", "145": "J", "146": "n", "147": "C", "148": "y", "149": "F", "150": "o", "151": "2", "152": "w", "153": "3", "154": "%", "155": "S", "156": "5", "157": "$", "158": "P", "159": "m", "160": "E", "161": "K", "162": "6", "163": "O", "164": "#", "165": "0", "166": "8", "167": "Q", "168": "Q", "169": "W", "170": "W", "171": "B", "172": "@", "173": "@", "174": "N", "175": "N", "176": "N", "177": "N", "178": "N", "179": "N", "180": "N", "181": "N", "182": "N", "183": "N", "184": "N", "185": "N", "186": "N", "187": "N", "188": "N", "189": "N", "190": "N", "191": "N", "192": "N", "193": "N", "194": "N", "195": "N", "196": "N", "197": "N", "198": "N", "199": "N", "200": "N", "201": "N", "202": "N", "203": "N", "204": "N", "205": "N", "206": "N", "207": "N", "208": "N", "209": "N", "210": "N", "211": "N", "212": "N", "213": "N", "214": "N", "215": "N", "216": "N", "217": "N", "218": "N", "219": "N", "220": "N", "221": "N", "222": "N", "223": "N", "224": "N", "225": "N", "226": "N", "227": "N", "228": "N", "229": "N", "230": "N", "231": "N", "232": "N", "233": "N", "234": "N", "235": "N", "236": "N", "237": "N", "238": "N", "239": "N", "240": "N", "241": "N", "242": "N", "243": "N", "244": "N", "245": "N", "246": "N", "247": "N", "248": "N", "249": "N", "250": "N", "251": "N", "252": "N", "253": "N", "254": "N", "255": "N"}